bancodadosmysql/__init__.py
bancodadosmysql/DatabaseManager.py
bancodadosmysql-0.1.5.dist-info/METADATA
bancodadosmysql-0.1.5.dist-info/WHEEL
bancodadosmysql-0.1.5.dist-info/RECORD
